{
    "@context": [
        "http://iiif.io/api/presentation/2/context.json",
        "http://codh.rois.ac.jp/iiif/curation/1/context.json"
    ],
    "@id": "https://nakamura196.github.io/E34/curation/2-3-/character.json",
    "@type": "cr:Curation",
    "selections": [
        {
            "@id": "https://nakamura196.github.io/E34/iiif/2-3-/manifest.json",
            "@type": "sc:Range",
            "members": [
                {
                    "@id": "https://nakamura196.github.io/E34/iiif/2-3-/canvas/p1#xywh=3430,1439,276,233",
                    "@type": "sc:Canvas",
                    "label": "34241265",
                    "metadata": [
                        {
                            "label": "Annotation",
                            "value": [
                                {
                                    "@id": "https://nakamura196.github.io/E34/iiif/2-3-/canvas/p1#xywh=3430,1439,276,233#34241265",
                                    "@type": "oa:Annotation",
                                    "motivation": "sc:painting",
                                    "on": "https://nakamura196.github.io/E34/iiif/2-3-/canvas/p1#xywh=3430,1439,276,233",
                                    "resource": {
                                        "@type": "cnt:ContentAsText",
                                        "chars": "null<br/><a href=\"https://hi-ut.github.io/kuzushiji/item/null/34241265\">U+</a>",
                                        "format": "text/html",
                                        "marker": {
                                            "text": "null"
                                        }
                                    }
                                }
                            ]
                        }
                    ]
                }
            ],
            "within": {
                "@id": "https://nakamura196.github.io/E34/iiif/2-3-/manifest.json",
                "@type": "sc:Manifest",
                "label": "御文書　廿五通[有忠宗裏判]一之巻　左衛門尉盛景(二五通)@ja"
            }
        }
    ],
    "viewingHint": "annotation"
}